LICENCE.txt
MANIFEST.in
README.rst
ez_setup.py
pypi-readme.rst
setup.py
examples/basic_success_rate_prediction.py
examples/plotting_interactions.py
examples/success_rate_facts.py
kappagate/__init__.py
kappagate/predict_assembly_accuracy.py
kappagate/reporting.py
kappagate/tools.py
kappagate/version.py
kappagate.egg-info/PKG-INFO
kappagate.egg-info/SOURCES.txt
kappagate.egg-info/dependency_links.txt
kappagate.egg-info/requires.txt
kappagate.egg-info/top_level.txt