Metadata-Version: 1.0
Name: kappagate
Version: 0.1.3
Summary: Predict valid-clone-rates in Golden Gate DNA assemblies
Home-page: https://github.com/Edinburgh-Genome-Foundry/kappagate
Author: Zulko
Author-email: UNKNOWN
License: MIT
Keywords: DNA assembly synthetic biology golden gate
Platform: UNKNOWN
